mylibisyourlib/__init__.py
mylibisyourlib/create_script.py
mylibisyourlib/fetch_content_not_found.py
mylibisyourlib/module1.py
mylibisyourlib/update_content_not_found.py
mylibisyourlib-0.2.dist-info/METADATA
mylibisyourlib-0.2.dist-info/WHEEL
mylibisyourlib-0.2.dist-info/top_level.txt
mylibisyourlib-0.2.dist-info/RECORD
