Metadata-Version: 2.1
Name: mylibisyourlib
Version: 0.2
Summary: A library for all people working on my project.
Author: Robin Messiaen
Author-email: robin_messiaen@hotmail.fr
Classifier: Programming Language :: Python :: 3
Classifier: License :: OSI Approved :: MIT License
Classifier: Operating System :: OS Independent
Requires-Python: >=3.6
Requires-Dist: requests
